flecs/__init__.py
flecs/__init__.pyi
flecs/_core.cpython-39-x86_64-linux-gnu.so
flecs/libflecs.so
include/flecs.h
include/flecs/bake_config.h
include/flecs/os_api.h
include/flecs/addons/alerts.h
include/flecs/addons/app.h
include/flecs/addons/deprecated.h
include/flecs/addons/doc.h
include/flecs/addons/flecs_c.h
include/flecs/addons/flecs_cpp.h
include/flecs/addons/http.h
include/flecs/addons/json.h
include/flecs/addons/log.h
include/flecs/addons/meta.h
include/flecs/addons/meta_c.h
include/flecs/addons/metrics.h
include/flecs/addons/module.h
include/flecs/addons/os_api_impl.h
include/flecs/addons/pipeline.h
include/flecs/addons/rest.h
include/flecs/addons/script.h
include/flecs/addons/script_math.h
include/flecs/addons/stats.h
include/flecs/addons/system.h
include/flecs/addons/timer.h
include/flecs/addons/units.h
include/flecs/addons/cpp/c_types.hpp
include/flecs/addons/cpp/component.hpp
include/flecs/addons/cpp/delegate.hpp
include/flecs/addons/cpp/entity.hpp
include/flecs/addons/cpp/entity_view.hpp
include/flecs/addons/cpp/field.hpp
include/flecs/addons/cpp/flecs.hpp
include/flecs/addons/cpp/iter.hpp
include/flecs/addons/cpp/lifecycle_traits.hpp
include/flecs/addons/cpp/log.hpp
include/flecs/addons/cpp/pair.hpp
include/flecs/addons/cpp/ref.hpp
include/flecs/addons/cpp/table.hpp
include/flecs/addons/cpp/type.hpp
include/flecs/addons/cpp/world.hpp
include/flecs/addons/cpp/impl/field.hpp
include/flecs/addons/cpp/impl/iter.hpp
include/flecs/addons/cpp/impl/world.hpp
include/flecs/addons/cpp/mixins/alerts/builder.hpp
include/flecs/addons/cpp/mixins/alerts/builder_i.hpp
include/flecs/addons/cpp/mixins/alerts/decl.hpp
include/flecs/addons/cpp/mixins/alerts/entity_view.inl
include/flecs/addons/cpp/mixins/alerts/impl.hpp
include/flecs/addons/cpp/mixins/alerts/mixin.inl
include/flecs/addons/cpp/mixins/app/builder.hpp
include/flecs/addons/cpp/mixins/app/decl.hpp
include/flecs/addons/cpp/mixins/app/mixin.inl
flecs-0.0.2.dist-info/METADATA
flecs-0.0.2.dist-info/WHEEL
flecs-0.0.2.dist-info/RECORD
flecs-0.0.2.dist-info/licenses/LICENSE
